platform_agent/__init__.py
platform_agent/cli.py
platform_agent/evaluator.py
ha_platform_agent-0.1.1.dist-info/METADATA
ha_platform_agent-0.1.1.dist-info/WHEEL
ha_platform_agent-0.1.1.dist-info/top_level.txt
ha_platform_agent-0.1.1.dist-info/RECORD
