Metadata-Version: 2.4
Name: ha-platform-agent
Version: 0.1.1
Summary: Agentic AI-powered platform evaluator for multi-cloud code and logic evaluation.
Author-email: srinivas-b-sindagi <seenu@hebbale.academy>
Requires-Python: >=3.9
Requires-Dist: google-adk
Requires-Dist: google-generativeai
